chippai/__init__.py
chippai/core.py
chippai/user.py
chippai-0.1.2.dist-info/METADATA
chippai-0.1.2.dist-info/WHEEL
chippai-0.1.2.dist-info/top_level.txt
chippai-0.1.2.dist-info/RECORD
