Metadata-Version: 2.1
Name: chippai
Version: 0.1.2
Summary: A Python wrapper for Chipp API
Author-email: Andre Lacke <andre@chipp.ai>
Project-URL: Homepage, https://github.com/benchmarkai/chippai-pip
Project-URL: Bug Tracker, https://github.com/benchmarkai/chippai-pip/issues
Classifier: Programming Language :: Python :: 3
Classifier: License :: OSI Approved :: MIT License
Classifier: Operating System :: OS Independent
Requires-Python: >=3.7
